{
  "date": "2026-07-08",
  "weekday": "周三",
  "updated": "2026-07-08 11:13:20 CST",
  "guides": [
    {
      "title": "保时捷联动卡池回顾与评价",
      "desc": "联动限定角色强度回顾，是否值得补票"
    },
    {
      "title": "1.1版本新弧盘强度测评",
      "desc": "夜曲特刊活动弧盘实战数据对比"
    }
  ],
  "news": [
    {
      "title": "同居系统隐藏对话整理",
      "desc": "不同角色邀请同居后的特殊对话和事件"
    },
    {
      "title": "开发组AMA答玩家问精华整理",
      "desc": "制作人在Discord的问答要点：未来更新方向"
    }
  ],
  "tips": [
    {
      "title": "联机模式礼仪指南",
      "desc": "进别人世界要注意什么？老玩家整理"
    },
    {
      "title": "免费回血点位汇总",
      "desc": "全地图8个免费回血地点，省下料理材料"
    }
  ]
}